anjl/__init__.py
anjl/_canonical.py
anjl/_dynamic.py
anjl/_layout.py
anjl/_plot.py
anjl/_rapid.py
anjl/_util.py
anjl/data.py
anjl/params.py
anjl/resources/mosquitoes.csv
anjl/resources/mosquitoes.npy
anjl/testing.py
anjl-1.4.0.dist-info/LICENSE
anjl-1.4.0.dist-info/METADATA
anjl-1.4.0.dist-info/WHEEL
anjl-1.4.0.dist-info/RECORD
